skill_custom_conversation/README.md
skill_custom_conversation/__init__.py
skill_custom_conversation/skill.json
skill_custom_conversation/test_utils.py
skill_custom_conversation/utils_emulate.py
skill_custom_conversation/version.py
skill_custom_conversation/dialog/en-us/AlreadyRunning.dialog
skill_custom_conversation/dialog/en-us/Exiting.dialog
skill_custom_conversation/dialog/en-us/NotFound.dialog
skill_custom_conversation/dialog/en-us/ProblemInFile.dialog
skill_custom_conversation/dialog/en-us/Starting.dialog
skill_custom_conversation/dialog/en-us/TimeoutExit.dialog
skill_custom_conversation/dialog/en-us/already_exists.dialog
skill_custom_conversation/dialog/en-us/already_filled.dialog
skill_custom_conversation/dialog/en-us/available_script.dialog
skill_custom_conversation/dialog/en-us/email_sent.dialog
skill_custom_conversation/dialog/en-us/error_at_line.dialog
skill_custom_conversation/dialog/en-us/new_existing.dialog
skill_custom_conversation/dialog/en-us/new_is_another_key.dialog
skill_custom_conversation/dialog/en-us/new_is_another_value.dialog
skill_custom_conversation/dialog/en-us/no_email.dialog
skill_custom_conversation/dialog/en-us/same_values.dialog
skill_custom_conversation/dialog/en-us/startup_script.dialog
skill_custom_conversation/dialog/en-us/update_disallowed.dialog
skill_custom_conversation/dialog/en-us/update_failed.dialog
skill_custom_conversation/dialog/en-us/update_started.dialog
skill_custom_conversation/dialog/en-us/update_success.dialog
skill_custom_conversation/dialog/en-us/upload_failed.dialog
skill_custom_conversation/dialog/en-us/upload_success.dialog
skill_custom_conversation/neon_skill_custom_conversation.egg-info/PKG-INFO
skill_custom_conversation/neon_skill_custom_conversation.egg-info/SOURCES.txt
skill_custom_conversation/neon_skill_custom_conversation.egg-info/dependency_links.txt
skill_custom_conversation/neon_skill_custom_conversation.egg-info/entry_points.txt
skill_custom_conversation/neon_skill_custom_conversation.egg-info/requires.txt
skill_custom_conversation/neon_skill_custom_conversation.egg-info/top_level.txt
skill_custom_conversation/regex/en-us/File_to_Run.rx
skill_custom_conversation/vocab/en-us/Neon.voc
skill_custom_conversation/vocab/en-us/UpdateScripts.voc
skill_custom_conversation/vocab/en-us/default.voc
skill_custom_conversation/vocab/en-us/email.voc
skill_custom_conversation/vocab/en-us/script.voc
skill_custom_conversation/vocab/en-us/tell.voc
neon_skill_custom_conversation-0.0.1a11.dist-info/METADATA
neon_skill_custom_conversation-0.0.1a11.dist-info/WHEEL
neon_skill_custom_conversation-0.0.1a11.dist-info/entry_points.txt
neon_skill_custom_conversation-0.0.1a11.dist-info/top_level.txt
neon_skill_custom_conversation-0.0.1a11.dist-info/RECORD
