Metadata-Version: 2.1
Name: neon-skill-custom-conversation
Version: 0.0.1a11
Home-page: https://github.com/NeonGeckoCom/skill-custom_conversation
Author: Neongecko
Author-email: developers@neon.ai
License: BSD-3-Clause
Requires-Dist: bs4
Requires-Dist: gitpython~=3.1
Requires-Dist: neon-utils~=1.12
Requires-Dist: ovos-utils>=0.0.28,~=0.0
Requires-Dist: ovos-bus-client>=0.0.3,~=0.0
Requires-Dist: ovos-workshop>=0.0.15,~=0.0
Requires-Dist: ovos-lingua-franca~=0.4
